{
    "line": {
      "groups": [
        {
          "title": "Paint properties",
          "type": "properties",
          "fields": [
            "line-opacity",
            "line-color",
            "line-width",
            "line-gap-width"
          ]
        }
      ]
    },
    "background": {
      "groups": [
        {
          "title": "Paint properties",
          "type": "properties",
          "fields": [
            "background-color",
            "background-opacity"
          ]
        }
      ]
    },
    "fill": {
      "groups": [
        {
          "title": "Paint properties",
          "type": "properties",
          "fields": [
            "fill-opacity",
            "fill-color",
            "fill-outline-color"
          ]
        }
      ]
    },
    "fill-extrusion": {
      "groups": [
        {
          "title": "Paint properties",
          "type": "properties",
          "fields": [
            "fill-extrusion-opacity",
            "fill-extrusion-color"
          ]
        }
      ]
    },
    "circle": {
      "groups": [
        {
          "title": "Paint properties",
          "type": "properties",
          "fields": [
            "circle-color",
            "circle-opacity",
            "circle-radius"
          ]
        }
      ]
    },
    "symbol": {
      "groups": [
        {
          "title": "Text layout properties",
          "type": "properties",
          "fields": [
            "text-size",
            "text-line-height",
            "text-max-width"
          ]
        },
        {
          "title": "Text paint properties",
          "type": "properties",
          "fields": [
            "text-color",
            "text-opacity",
            "text-halo-color",
            "text-halo-width",
            "text-halo-blur"
          ]
        }
      ]
    },
    "raster": {
      "groups": [
        {
          "title": "Paint properties",
          "type": "properties",
          "fields": [
            "raster-opacity",
            "raster-hue-rotate",
            "raster-brightness-min",
            "raster-brightness-max"
          ]
        }
      ]
    },
    "hillshade": {
      "groups": [
        {
          "title": "Paint properties",
          "type": "properties",
          "fields": [
            "hillshade-shadow-color",
            "hillshade-highlight-color",
            "hillshade-accent-color"
          ]
        }
      ]
    },
    "heatmap": {
      "groups": [
        {
          "title": "Paint properties",
          "type": "properties",
          "fields": [
            "heatmap-radius",
            "heatmap-weight",
            "heatmap-intensity",
            "heatmap-opacity"
          ]
        }
      ]
    },
    "invalid": {
      "groups": []
    }
}
